requeriments.txt
networktools/annalysis.py
networktools/channel.py
networktools/colorprint.py
networktools/docmethod.py
networktools/environment.py
networktools/factory.py
networktools/geo.py
networktools/gui.py
networktools/ip.py
networktools/library.py
networktools/ports.py
networktools/queue.py
networktools/requeriments.py
networktools/ssh.py
networktools/statistics.py
networktools/text.py
networktools/time.py
networktools-0.7.3.dist-info/LICENSE
networktools-0.7.3.dist-info/LICENSE.txt
networktools-0.7.3.dist-info/METADATA
networktools-0.7.3.dist-info/WHEEL
networktools-0.7.3.dist-info/top_level.txt
networktools-0.7.3.dist-info/RECORD
