Metadata-Version: 2.1
Name: networktools
Version: 0.7.3
Summary: NetworkTools are some special functions to help with software developing
Home-page: http://www.gitlab.com/dpineda/networktools
Author: David Pineda Osorio
Author-email: dpineda@csn.uchile.cl
License: GPL3
Platform: UNKNOWN
